sensirion_i2c_svm40/__init__.py
sensirion_i2c_svm40/device.py
sensirion_i2c_svm40/response_types.py
sensirion_i2c_svm40/version.py
sensirion_i2c_svm40/version_types.py
sensirion_i2c_svm40/commands/__init__.py
sensirion_i2c_svm40/commands/generated.py
sensirion_i2c_svm40/commands/wrapped.py
sensirion_i2c_svm40-0.1.1.dist-info/LICENSE
sensirion_i2c_svm40-0.1.1.dist-info/METADATA
sensirion_i2c_svm40-0.1.1.dist-info/WHEEL
sensirion_i2c_svm40-0.1.1.dist-info/top_level.txt
sensirion_i2c_svm40-0.1.1.dist-info/RECORD
